swarmauri_certs_x509verify/X509VerifyService.py
swarmauri_certs_x509verify/__init__.py
swarmauri_certs_x509verify-0.3.0.dev4.dist-info/LICENSE
swarmauri_certs_x509verify-0.3.0.dev4.dist-info/METADATA
swarmauri_certs_x509verify-0.3.0.dev4.dist-info/WHEEL
swarmauri_certs_x509verify-0.3.0.dev4.dist-info/entry_points.txt
swarmauri_certs_x509verify-0.3.0.dev4.dist-info/RECORD
